{
  "$schema": "https://developer.microsoft.com/json-schemas/fabric/item/report/definition/visualContainer/2.1.0/schema.json",
  "name": "2db0b0cb16ef313b0145",
  "position": {
    "x": 251.59705159705157,
    "y": 0,
    "z": 8000,
    "height": 117.93611793611792,
    "width": 316.068796068796,
    "tabOrder": 8000
  },
  "visual": {
    "visualType": "card",
    "query": {
      "queryState": {
        "Values": {
          "projections": [
            {
              "field": {
                "Aggregation": {
                  "Expression": {
                    "Column": {
                      "Expression": {
                        "SourceRef": {
                          "Entity": "Appointments"
                        }
                      },
                      "Property": "Cancelled At"
                    }
                  },
                  "Function": 5
                }
              },
              "queryRef": "Min(Appointments.Cancelled At)",
              "nativeQueryRef": "Count of Cancelled At"
            }
          ]
        }
      },
      "sortDefinition": {
        "sort": [
          {
            "field": {
              "Aggregation": {
                "Expression": {
                  "Column": {
                    "Expression": {
                      "SourceRef": {
                        "Entity": "Appointments"
                      }
                    },
                    "Property": "Cancelled At"
                  }
                },
                "Function": 5
              }
            },
            "direction": "Descending"
          }
        ],
        "isDefaultSort": true
      }
    },
    "objects": {
      "labels": [
        {
          "properties": {
            "labelPrecision": {
              "expr": {
                "Literal": {
                  "Value": "2L"
                }
              }
            },
            "preserveWhitespace": {
              "expr": {
                "Literal": {
                  "Value": "true"
                }
              }
            },
            "color": {
              "solid": {
                "color": {
                  "expr": {
                    "ThemeDataColor": {
                      "ColorId": 0,
                      "Percent": 0
                    }
                  }
                }
              }
            }
          }
        }
      ],
      "categoryLabels": [
        {
          "properties": {
            "show": {
              "expr": {
                "Literal": {
                  "Value": "false"
                }
              }
            }
          }
        }
      ]
    },
    "visualContainerObjects": {
      "border": [
        {
          "properties": {
            "show": {
              "expr": {
                "Literal": {
                  "Value": "false"
                }
              }
            },
            "radius": {
              "expr": {
                "Literal": {
                  "Value": "6D"
                }
              }
            },
            "color": {
              "solid": {
                "color": {
                  "expr": {
                    "Literal": {
                      "Value": "'#3C5F88'"
                    }
                  }
                }
              }
            }
          }
        }
      ],
      "title": [
        {
          "properties": {
            "show": {
              "expr": {
                "Literal": {
                  "Value": "true"
                }
              }
            },
            "text": {
              "expr": {
                "Literal": {
                  "Value": "'Total Cancellations'"
                }
              }
            },
            "alignment": {
              "expr": {
                "Literal": {
                  "Value": "'center'"
                }
              }
            },
            "heading": {
              "expr": {
                "Literal": {
                  "Value": "'Heading3'"
                }
              }
            },
            "background": {
              "solid": {
                "color": {
                  "expr": {
                    "Literal": {
                      "Value": "'#3C5F88'"
                    }
                  }
                }
              }
            },
            "fontColor": {
              "solid": {
                "color": {
                  "expr": {
                    "ThemeDataColor": {
                      "ColorId": 2,
                      "Percent": 0.6
                    }
                  }
                }
              }
            },
            "fontSize": {
              "expr": {
                "Literal": {
                  "Value": "18D"
                }
              }
            }
          }
        }
      ],
      "general": [
        {
          "properties": {
            "keepLayerOrder": {
              "expr": {
                "Literal": {
                  "Value": "false"
                }
              }
            }
          }
        }
      ],
      "background": [
        {
          "properties": {
            "color": {
              "solid": {
                "color": {
                  "expr": {
                    "Literal": {
                      "Value": "'#3C5F88'"
                    }
                  }
                }
              }
            },
            "show": {
              "expr": {
                "Literal": {
                  "Value": "true"
                }
              }
            }
          }
        }
      ],
      "subTitle": [
        {
          "properties": {
            "show": {
              "expr": {
                "Literal": {
                  "Value": "false"
                }
              }
            },
            "text": {
              "expr": {
                "Literal": {
                  "Value": "''"
                }
              }
            },
            "fontColor": {
              "solid": {
                "color": {
                  "expr": {
                    "ThemeDataColor": {
                      "ColorId": 0,
                      "Percent": 0
                    }
                  }
                }
              }
            }
          }
        }
      ],
      "padding": [
        {
          "properties": {
            "top": {
              "expr": {
                "Literal": {
                  "Value": "5D"
                }
              }
            }
          }
        }
      ]
    },
    "drillFilterOtherVisuals": true
  }
}